notification_system/__init__.py
notification_system/admin.py
notification_system/apps.py
notification_system/managers.py
notification_system/models.py
notification_system/notification_delivery.py
notification_system/paginations.py
notification_system/parsers.py
notification_system/permissions.py
notification_system/tasks.py
notification_system/tests.py
notification_system/urls.py
notification_system/utils.py
notification_system/validators.py
notification_system/views.py
notification_system/api/__init__.py
notification_system/api/serializers.py
notification_system/api/urls.py
notification_system/api/views.py
notification_system/common/__init__.py
notification_system/common/notification_handler.py
notification_system/migrations/0001_initial.py
notification_system/migrations/0002_auto_20220713_1151.py
notification_system/migrations/0003_auto_20220716_0639.py
notification_system/migrations/0004_auto_20220723_1247.py
notification_system/migrations/0005_auto_20220725_1312.py
notification_system/migrations/0006_auto_20230109_1407.py
notification_system/migrations/__init__.py
drf_notification_system-1.3.0.dist-info/LICENSE
drf_notification_system-1.3.0.dist-info/METADATA
drf_notification_system-1.3.0.dist-info/WHEEL
drf_notification_system-1.3.0.dist-info/top_level.txt
drf_notification_system-1.3.0.dist-info/RECORD
