Metadata-Version: 2.1
Name: drf-notification-system
Version: 1.3.0
Summary: A Django app to sends notifications to internal users.
Home-page: https://pypi.org/project/drf-notification-system/
Author: Mahdi Rahimi
Author-email: mahdi.rahimi95@gmail.com
License: MIT
Platform: UNKNOWN
Classifier: Environment :: Web Environment
Classifier: Framework :: Django
Classifier: Intended Audience :: Developers
Classifier: License :: OSI Approved :: MIT License
Classifier: Operating System :: OS Independent
Classifier: Programming Language :: Python
Classifier: Programming Language :: Python :: 3
Requires-Python: >=3.6
License-File: LICENSE
